pyTUID/__init__.py
pyTUID/admin.py
pyTUID/apps.py
pyTUID/decorators.py
pyTUID/middleware.py
pyTUID/mixins.py
pyTUID/models.py
pyTUID/settings.py
pyTUID/tests.py
pyTUID/urls.py
pyTUID/util.py
pyTUID/views.py
pyTUID/migrations/0001_initial.py
pyTUID/migrations/0002_auto_20170418_1356.py
pyTUID/migrations/0003_auto_20170514_1146.py
pyTUID/migrations/0004_auto_20170903_1902.py
pyTUID/migrations/0005_auto_20190308_1132.py
pyTUID/migrations/__init__.py
pyTUID-1.3.5.dist-info/LICENSE.txt
pyTUID-1.3.5.dist-info/METADATA
pyTUID-1.3.5.dist-info/WHEEL
pyTUID-1.3.5.dist-info/top_level.txt
pyTUID-1.3.5.dist-info/RECORD
