Metadata-Version: 2.1
Name: pyTUID
Version: 1.3.5
Summary: Django app for authentication via TUID (CAS)
Home-page: https://github.com/d120/pyTUID
Author: Fabian Franke
Author-email: ffranke@d120.de
License: MIT
Platform: UNKNOWN
Classifier: Environment :: Web Environment
Classifier: Framework :: Django
Classifier: Operating System :: OS Independent
Classifier: Programming Language :: Python
Classifier: Programming Language :: Python :: 3
Requires-Dist: python-cas
